Metadata-Version: 2.1
Name: modern-django-starter
Version: 0.2.3
Summary: A CLI tool for generating Django 5.x projects with HTMX, AlpineJS, and more
Author-email: Rian <rian@pythonist.dev>
License: MIT
Project-URL: Homepage, https://github.com/CasualEngineerZombie/modern-django-starter
Project-URL: Repository, https://github.com/CasualEngineerZombie/modern-django-starter
Project-URL: Issues, https://github.com/CasualEngineerZombie/modern-django-starter/issues
Keywords: django,htmx,alpine,tailwind,starter,boilerplate
Classifier: Development Status :: 3 - Alpha
Classifier: Intended Audience :: Developers
Classifier: License :: OSI Approved :: MIT License
Classifier: Programming Language :: Python :: 3
Classifier: Programming Language :: Python :: 3.8
Classifier: Programming Language :: Python :: 3.9
Classifier: Programming Language :: Python :: 3.10
Classifier: Programming Language :: Python :: 3.11
Classifier: Programming Language :: Python :: 3.12
Classifier: Framework :: Django
Classifier: Topic :: Software Development :: Code Generators
Requires-Python: >=3.8
Requires-Dist: click>=8.0.0
Requires-Dist: jinja2>=3.0.0
Requires-Dist: cookiecutter>=2.0.0
Requires-Dist: pyyaml>=6.0
Requires-Dist: rich>=13.0.0
